Metadata-Version: 1.1
Name: htmltemplate
Version: 2.2.1
Summary: A simple, powerful [X]HTML templating library for Python 3
Home-page: https://github.com/hhas/htmltemplate
Author: HAS
Author-email: hhas@users.sourceforge.net
License: UNKNOWN
Platform: UNKNOWN
Classifier: Development Status :: 5 - Production/Stable
Classifier: License :: OSI Approved :: MIT License
Classifier: Programming Language :: Python :: 3
Classifier: Topic :: Internet :: WWW/HTTP :: Dynamic Content :: CGI Tools/Libraries
